<?xml version="1.0" encoding="UTF-8"?>
<!DOCTYPE hibernate-mapping PUBLIC "-//Hibernate/Hibernate Mapping DTD 3.0//EN" "http://www.hibernate.org/dtd/hibernate-mapping-3.0.dtd">
<!-- Generated 15/06/2019 08:00:53 PM by Hibernate Tools 4.3.1 -->
<hibernate-mapping>
  <class name="com.nafsolver.entity.Argetb" optimistic-lock="version" schema="DESA46" table="ARGETB">
    <comment>Tabla de bancos</comment>
    <id name="banco" type="string">
      <column length="2" name="BANCO"/>
      <generator class="assigned"/>
    </id>
    <property name="descripcion" type="string">
      <column length="60" name="DESCRIPCION"/>
    </property>
    <property name="codigoTercero" type="string">
      <column length="18" name="CODIGO_TERCERO"/>
    </property>
  </class>
</hibernate-mapping>
